brainles_hd_bet/__init__.py
brainles_hd_bet/config.py
brainles_hd_bet/data_loading.py
brainles_hd_bet/hd_bet.py
brainles_hd_bet/network_architecture.py
brainles_hd_bet/predict_case.py
brainles_hd_bet/run.py
brainles_hd_bet/utils.py
brainles_hd_bet-0.0.11.dist-info/LICENSE
brainles_hd_bet-0.0.11.dist-info/METADATA
brainles_hd_bet-0.0.11.dist-info/WHEEL
brainles_hd_bet-0.0.11.dist-info/entry_points.txt
brainles_hd_bet-0.0.11.dist-info/RECORD
