Metadata-Version: 2.3
Name: brainles_hd_bet
Version: 0.0.11
Summary: TODO.
License: AGPL-3.0
Keywords: Brain extraction, skull stripping
Author: Florian Kofler
Author-email: florian.kofler@tum.de
Maintainer: Florian Kofler
Maintainer-email: florian.kofler@tum.de
Requires-Python: >=3.8
Classifier: License :: OSI Approved :: GNU Affero General Public License v3
Classifier: Operating System :: OS Independent
Classifier: Programming Language :: Python :: 3
Classifier: Programming Language :: Python :: 3.8
Classifier: Programming Language :: Python :: 3.9
Classifier: Programming Language :: Python :: 3.10
Classifier: Programming Language :: Python :: 3.11
Classifier: Programming Language :: Python :: 3.12
Classifier: Programming Language :: Python :: 3.13
Requires-Dist: SimpleITK (>=2.2.1)
Requires-Dist: numpy (>=1.24.0)
Requires-Dist: scikit-image (>=0.21.0)
Requires-Dist: torch (>=0.4.1)
Project-URL: Repository, https://github.com/BrainLesion/HD-BET
